[
  {
    "symbol": "RENDERUSDT",
    "backtest": {
      "trades": 9,
      "wins": 0,
      "losses": 9,
      "win_rate": 0.0,
      "avg_win_pct": 0.0,
      "avg_loss_pct": 6.35,
      "ev": -1.0,
      "score": -0.0
    },
    "current_state": {
      "symbol": "RENDERUSDT",
      "price": 1.577,
      "rsi": 54.2,
      "atr": 0.02109972,
      "vol_ratio": 0.11,
      "vol_label": "low",
      "ema20": 1.56827885,
      "ema50": 1.57119769,
      "ema200": 1.63826592,
      "ema_pos": [
        "above EMA20",
        "above EMA50",
        "below EMA200"
      ],
      "rsi_trend": [
        54.2,
        53.4,
        53.8,
        53.8,
        54.2
      ],
      "sl": 1.55767008,
      "tp": 1.61565983,
      "sl_pct": 1.23,
      "tp_pct": 2.45,
      "last_dt": "2026-07-11 20:00 UTC",
      "last_ts_ms": 1783800000000,
      "curr_signals": []
    }
  },
  {
    "symbol": "LINKUSDT",
    "backtest": {
      "trades": 3,
      "wins": 1,
      "losses": 2,
      "win_rate": 33.3,
      "avg_win_pct": 5.72,
      "avg_loss_pct": 4.96,
      "ev": 0.0,
      "score": 0.0
    },
    "current_state": {
      "symbol": "LINKUSDT",
      "price": 8.0723,
      "rsi": 64.2,
      "atr": 0.09890613,
      "vol_ratio": 0.08,
      "vol_label": "low",
      "ema20": 7.93139894,
      "ema50": 7.84648665,
      "ema200": 7.92223947,
      "ema_pos": [
        "above EMA20",
        "above EMA50",
        "above EMA200"
      ],
      "rsi_trend": [
        60.3,
        60.9,
        64.3,
        65.2,
        64.2
      ],
      "sl": 7.94272816,
      "tp": 8.33144368,
      "sl_pct": 1.61,
      "tp_pct": 3.21,
      "last_dt": "2026-07-11 20:00 UTC",
      "last_ts_ms": 1783800000000,
      "curr_signals": []
    }
  },
  {
    "symbol": "DOGEUSDT",
    "backtest": {
      "trades": 5,
      "wins": 0,
      "losses": 5,
      "win_rate": 0.0,
      "avg_win_pct": 0.0,
      "avg_loss_pct": 3.42,
      "ev": -1.0,
      "score": -0.0
    },
    "current_state": {
      "symbol": "DOGEUSDT",
      "price": 0.07518,
      "rsi": 59.7,
      "atr": 0.00088224,
      "vol_ratio": 0.1,
      "vol_label": "low",
      "ema20": 0.074282,
      "ema50": 0.07452768,
      "ema200": 0.07982808,
      "ema_pos": [
        "above EMA20",
        "above EMA50",
        "below EMA200"
      ],
      "rsi_trend": [
        52.8,
        54.6,
        61.5,
        61.8,
        59.7
      ],
      "sl": 0.07387533,
      "tp": 0.07778934,
      "sl_pct": 1.74,
      "tp_pct": 3.47,
      "last_dt": "2026-07-11 20:00 UTC",
      "last_ts_ms": 1783800000000,
      "curr_signals": []
    }
  },
  {
    "symbol": "ONDOUSDT",
    "backtest": {
      "trades": 11,
      "wins": 1,
      "losses": 10,
      "win_rate": 9.1,
      "avg_win_pct": 9.99,
      "avg_loss_pct": 6.1,
      "ev": -0.727,
      "score": -0.0661
    },
    "current_state": {
      "symbol": "ONDOUSDT",
      "price": 0.33445,
      "rsi": 62.0,
      "atr": 0.0059078,
      "vol_ratio": 0.06,
      "vol_label": "low",
      "ema20": 0.32754871,
      "ema50": 0.32624208,
      "ema200": 0.33357575,
      "ema_pos": [
        "above EMA20",
        "above EMA50",
        "above EMA200"
      ],
      "rsi_trend": [
        53.9,
        61.5,
        62.2,
        62.4,
        62.0
      ],
      "sl": 0.32448766,
      "tp": 0.35437468,
      "sl_pct": 2.98,
      "tp_pct": 5.96,
      "last_dt": "2026-07-11 20:00 UTC",
      "last_ts_ms": 1783800000000,
      "curr_signals": []
    }
  },
  {
    "symbol": "HBARUSDT",
    "backtest": {
      "trades": 9,
      "wins": 1,
      "losses": 8,
      "win_rate": 11.1,
      "avg_win_pct": 16.79,
      "avg_loss_pct": 3.78,
      "ev": -0.667,
      "score": -0.0741
    },
    "current_state": {
      "symbol": "HBARUSDT",
      "price": 0.06978,
      "rsi": 44.7,
      "atr": 0.00127042,
      "vol_ratio": 0.12,
      "vol_label": "low",
      "ema20": 0.07029931,
      "ema50": 0.07127797,
      "ema200": 0.07575963,
      "ema_pos": [
        "below EMA20",
        "below EMA50",
        "below EMA200"
      ],
      "rsi_trend": [
        48.3,
        36.9,
        45.5,
        45.8,
        44.7
      ],
      "sl": 0.06620888,
      "tp": 0.07692225,
      "sl_pct": 5.12,
      "tp_pct": 10.24,
      "last_dt": "2026-07-11 20:00 UTC",
      "last_ts_ms": 1783800000000,
      "curr_signals": []
    }
  },
  {
    "symbol": "FETUSDT",
    "backtest": {
      "trades": 8,
      "wins": 1,
      "losses": 7,
      "win_rate": 12.5,
      "avg_win_pct": 8.67,
      "avg_loss_pct": 8.11,
      "ev": -0.625,
      "score": -0.0781
    },
    "current_state": {
      "symbol": "FETUSDT",
      "price": 0.1627,
      "rsi": 47.6,
      "atr": 0.00283498,
      "vol_ratio": 0.06,
      "vol_label": "low",
      "ema20": 0.16258746,
      "ema50": 0.16680572,
      "ema200": 0.18312928,
      "ema_pos": [
        "above EMA20",
        "below EMA50",
        "below EMA200"
      ],
      "rsi_trend": [
        43.6,
        46.0,
        48.1,
        48.4,
        47.6
      ],
      "sl": 0.16004951,
      "tp": 0.16800099,
      "sl_pct": 1.63,
      "tp_pct": 3.26,
      "last_dt": "2026-07-11 20:00 UTC",
      "last_ts_ms": 1783800000000,
      "curr_signals": []
    }
  },
  {
    "symbol": "TAOUSDT",
    "backtest": {
      "trades": 7,
      "wins": 1,
      "losses": 6,
      "win_rate": 14.3,
      "avg_win_pct": 9.85,
      "avg_loss_pct": 3.84,
      "ev": -0.571,
      "score": -0.0816
    },
    "current_state": {
      "symbol": "TAOUSDT",
      "price": 214.17,
      "rsi": 56.9,
      "atr": 3.65138519,
      "vol_ratio": 0.11,
      "vol_label": "low",
      "ema20": 211.86748982,
      "ema50": 211.46607927,
      "ema200": 221.40062873,
      "ema_pos": [
        "above EMA20",
        "above EMA50",
        "below EMA200"
      ],
      "rsi_trend": [
        53.9,
        54.0,
        53.5,
        56.8,
        56.9
      ],
      "sl": 210.53458444,
      "tp": 221.44083112,
      "sl_pct": 1.7,
      "tp_pct": 3.39,
      "last_dt": "2026-07-11 20:00 UTC",
      "last_ts_ms": 1783800000000,
      "curr_signals": []
    }
  }
]